LOGIA AI/__init__.py
logia/__init__.py
logia-0.0.2.dist-info/METADATA
logia-0.0.2.dist-info/WHEEL
logia-0.0.2.dist-info/top_level.txt
logia-0.0.2.dist-info/RECORD
