Metadata-Version: 2.1
Name: logia
Version: 0.0.2
Summary: Simply printing Hello from Logia :)
Home-page: 
Author: 
Author-email: 
Classifier: Programming Language :: Python :: 3
Requires-Python: >=3.6
